openedx_filters/__init__.py
openedx_filters/exceptions.py
openedx_filters/filters.py
openedx_filters/tooling.py
openedx_filters/utils.py
openedx_filters/content_authoring/__init__.py
openedx_filters/content_authoring/filters.py
openedx_filters/content_authoring/tests/__init__.py
openedx_filters/content_authoring/tests/test_filters.py
openedx_filters/learning/__init__.py
openedx_filters/learning/filters.py
openedx_filters/learning/tests/__init__.py
openedx_filters/learning/tests/test_filters.py
openedx_filters/tests/__init__.py
openedx_filters/tests/test_exceptions.py
openedx_filters/tests/test_filters.py
openedx_filters/tests/test_tooling.py
openedx_filters-2.1.0.dist-info/licenses/LICENSE.txt
openedx_filters-2.1.0.dist-info/METADATA
openedx_filters-2.1.0.dist-info/WHEEL
openedx_filters-2.1.0.dist-info/top_level.txt
openedx_filters-2.1.0.dist-info/RECORD
